pytml-0.2.2.dist-info/DESCRIPTION.rst
pytml-0.2.2.dist-info/METADATA
pytml-0.2.2.dist-info/metadata.json
pytml-0.2.2.dist-info/RECORD
pytml-0.2.2.dist-info/top_level.txt
pytml-0.2.2.dist-info/WHEEL
tests/integration/__init__.py
tests/integration/cache.py
tests/integration/context.py
tests/mock/__init__.py
tests/mock/fallback.py
tests/performance/__init__.py
tests/performance/check.py
tests/unit/__init__.py
tests/unit/application.py
tests/unit/common.py
tests/unit/decoration.py
tests/unit/language.py
tests/unit/legacy.py
tests/unit/logger.py
tests/unit/api/__init__.py
tests/unit/api/client.py
tests/unit/api/pagination.py
tests/unit/api/snapshot.py
tests/unit/dictionary/__init__.py
tests/unit/dictionary/language.py
tests/unit/dictionary/snapshot.py
tests/unit/dictionary/source.py
tests/unit/dictionary/translations.py
tests/unit/rules/__init__.py
tests/unit/rules/case.py
tests/unit/rules/engine.py
tests/unit/rules/functions.py
tests/unit/rules/options.py
tests/unit/rules/parser.py
tests/unit/rules/contexts/__init__.py
tests/unit/rules/contexts/count.py
tests/unit/rules/contexts/date.py
tests/unit/rules/contexts/gender.py
tests/unit/rules/contexts/genders.py
tests/unit/rules/contexts/number.py
tests/unit/token/__init__.py
tests/unit/token/parser.py
tests/unit/tools/__init__.py
tests/unit/tools/list.py
tests/unit/tools/viewing_user.py
tests/unit/translation/__init__.py
tests/unit/translation/missed.py
tml/__init__.py
tml/application.py
tml/base.py
tml/cache.py
tml/config.py
tml/context.py
tml/exceptions.py
tml/language.py
tml/legacy.py
tml/logger.py
tml/render.py
tml/session_vars.py
tml/source.py
tml/strings.py
tml/translator.py
tml/utils.py
tml/api/__init__.py
tml/api/client.py
tml/api/mock.py
tml/api/pagination.py
tml/api/snapshot.py
tml/cache_adapters/__init__.py
tml/cache_adapters/codecs.py
tml/cache_adapters/file.py
tml/cache_adapters/memcached.py
tml/cache_adapters/test_utils.py
tml/decoration/__init__.py
tml/decoration/parser.py
tml/defaults/languages/en.json
tml/dictionary/__init__.py
tml/dictionary/language.py
tml/dictionary/snapshot.py
tml/dictionary/source.py
